AUTHORS
ChangeLog
README.rst
requirements.txt
setup.cfg
setup.py
git_query/__init__.py
git_query/api.py
git_query/constants.py
git_query/query.py
git_query/shell.py
git_query.egg-info/PKG-INFO
git_query.egg-info/SOURCES.txt
git_query.egg-info/dependency_links.txt
git_query.egg-info/entry_points.txt
git_query.egg-info/not-zip-safe
git_query.egg-info/pbr.json
git_query.egg-info/requires.txt
git_query.egg-info/top_level.txt