Metadata-Version: 1.0
Name: git-query
Version: 0.0.1
Summary: Tool to query info from Gerrit like pending reviews
Home-page: https://github.com/sudocode/git-query
Author: Daniel Park
Author-email: sudocoder@ymail.com
License: MIT
Keywords: gerrit
Platform: UNKNOWN
